LICENSE.txt
MANIFEST.in
README.md
pyproject.toml
setup.cfg
setup.py
neuropythy/__init__.py
neuropythy/__main__.py
neuropythy.egg-info/PKG-INFO
neuropythy.egg-info/SOURCES.txt
neuropythy.egg-info/dependency_links.txt
neuropythy.egg-info/requires.txt
neuropythy.egg-info/top_level.txt
neuropythy/commands/__init__.py
neuropythy/commands/atlas.py
neuropythy/commands/benson14_retinotopy.py
neuropythy/commands/register_retinotopy.py
neuropythy/commands/retinotopy.py
neuropythy/commands/surface_to_image.py
neuropythy/datasets/__init__.py
neuropythy/datasets/benson_winawer_2018.py
neuropythy/datasets/core.py
neuropythy/datasets/hcp.py
neuropythy/datasets/hcp_lines.py
neuropythy/datasets/visual_performance_fields.py
neuropythy/freesurfer/__init__.py
neuropythy/freesurfer/core.py
neuropythy/geometry/__init__.py
neuropythy/geometry/mesh.py
neuropythy/geometry/util.py
neuropythy/graphics/__init__.py
neuropythy/graphics/core.py
neuropythy/hcp/__init__.py
neuropythy/hcp/core.py
neuropythy/hcp/files.py
neuropythy/io/__init__.py
neuropythy/io/core.py
neuropythy/java/__init__.py
neuropythy/lib/data/hcp_lines_osftree.json.gz
neuropythy/lib/data/fs_LR/lh.atlasroi.164k_fs_LR.shape.gii
neuropythy/lib/data/fs_LR/lh.atlasroi.32k_fs_LR.shape.gii
neuropythy/lib/data/fs_LR/lh.atlasroi.59k_fs_LR.shape.gii
neuropythy/lib/data/fs_LR/rh.atlasroi.164k_fs_LR.shape.gii
neuropythy/lib/data/fs_LR/rh.atlasroi.32k_fs_LR.shape.gii
neuropythy/lib/data/fs_LR/rh.atlasroi.59k_fs_LR.shape.gii
neuropythy/lib/data/fsaverage/surf/lh.benson14_angle.v4_0.mgz
neuropythy/lib/data/fsaverage/surf/lh.benson14_eccen.v4_0.mgz
neuropythy/lib/data/fsaverage/surf/lh.benson14_retinotopy.v4_0.sphere.reg
neuropythy/lib/data/fsaverage/surf/lh.benson14_sigma.v4_0.mgz
neuropythy/lib/data/fsaverage/surf/lh.benson14_varea.v4_0.mgz
neuropythy/lib/data/fsaverage/surf/lh.glasser16_atlas.v1_0.mgz
neuropythy/lib/data/fsaverage/surf/lh.rosenke18_vcatlas.v1_0.mgz
neuropythy/lib/data/fsaverage/surf/lh.wang15_fplbl.v1_0.mgz
neuropythy/lib/data/fsaverage/surf/lh.wang15_mplbl.v1_0.mgz
neuropythy/lib/data/fsaverage/surf/rh.benson14_angle.v4_0.mgz
neuropythy/lib/data/fsaverage/surf/rh.benson14_eccen.v4_0.mgz
