Metadata-Version: 2.1
Name: neuropythy
Version: 0.12.13
Summary: Toolbox for flexible cortical mesh analysis and registration
Home-page: https://github.com/noahbenson/neuropythy
Download-URL: https://github.com/noahbenson/neuropythy
Author: Noah C. Benson
Author-email: nben@uw.edu
Maintainer-email: nben@uw.edu
License: AGPL
Keywords: neuroscience mesh cortex registration
Classifier: Development Status :: 3 - Alpha
Classifier: Intended Audience :: Science/Research
Classifier: Intended Audience :: Developers
Classifier: License :: OSI Approved :: GNU Affero General Public License v3 or later (AGPLv3+)
Classifier: Programming Language :: Python :: 3
Classifier: Programming Language :: Python :: 3.6
Classifier: Programming Language :: Python :: 3.7
Classifier: Programming Language :: Python :: 3.8
Classifier: Programming Language :: Python :: 3.9
Classifier: Programming Language :: Python :: 3.10
Classifier: Programming Language :: Python :: 3.11
Classifier: Topic :: Software Development
Classifier: Topic :: Software Development :: Libraries
Classifier: Topic :: Software Development :: Libraries :: Python Modules
Classifier: Topic :: Scientific/Engineering
Classifier: Topic :: Scientific/Engineering :: Information Analysis
Classifier: Topic :: Scientific/Engineering :: Medical Science Apps.
Classifier: Operating System :: Microsoft :: Windows
Classifier: Operating System :: POSIX
Classifier: Operating System :: Unix
Classifier: Operating System :: MacOS
Provides-Extra: graphics2D
Provides-Extra: graphics3D
Provides-Extra: torch
Provides-Extra: all
License-File: LICENSE.txt
